setup.cfg
setup.py
markovlib/__init__.py
markovlib/backwards_compat.py
markovlib/markovutils.py
markovlib.egg-info/PKG-INFO
markovlib.egg-info/SOURCES.txt
markovlib.egg-info/dependency_links.txt
markovlib.egg-info/top_level.txt