Metadata-Version: 1.1
Name: markovlib
Version: 0.1
Summary: Simple implementation of Markov Modeller for abstract lists.
Home-page: https://github.com/bashia/markovlib
Author: Tony Bashi
Author-email: bashia@uvic.ca
License: GPL v2
Download-URL: https://github.com/bashia/markovlib/tarball/0.1
Platform: UNKNOWN
